celerytimer/__init__.py
celerytimer/cache.py
celerytimer/celerytimer.py
celerytimer/config.py
celerytimer/mysqldb.py
celerytimer-1.2.dist-info/LICENSE
celerytimer-1.2.dist-info/METADATA
celerytimer-1.2.dist-info/WHEEL
celerytimer-1.2.dist-info/top_level.txt
celerytimer-1.2.dist-info/RECORD
