Metadata-Version: 2.1
Name: celerytimer
Version: 1.2
Summary: Celery-based timing tasks
Home-page: https://github.com/dteer
Author: dteer
Author-email: dteer@qq.com
License: UNKNOWN
Platform: UNKNOWN
Classifier: Programming Language :: Python :: 3
Classifier: License :: OSI Approved :: MIT License
Classifier: Operating System :: OS Independent
